{
	"configurations" : 
	[
		{
			"directories" : 
			[
				{
					"build" : ".",
					"jsonFile" : "directory-.-Debug-f5ebdc15457944623624.json",
					"minimumCMakeVersion" : 
					{
						"string" : "3.29"
					},
					"projectIndex" : 0,
					"source" : ".",
					"targetIndexes" : 
					[
						0
					]
				}
			],
			"name" : "Debug",
			"projects" : 
			[
				{
					"directoryIndexes" : 
					[
						0
					],
					"name" : "Matam_HW4",
					"targetIndexes" : 
					[
						0
					]
				}
			],
			"targets" : 
			[
				{
					"directoryIndex" : 0,
					"id" : "Matam_HW4::@6890427a1f51a3e7e1df",
					"jsonFile" : "target-Matam_HW4-Debug-867a56de4e7e4a4b1d0a.json",
					"name" : "Matam_HW4",
					"projectIndex" : 0
				}
			]
		}
	],
	"kind" : "codemodel",
	"paths" : 
	{
		"build" : "/Users/ido/Documents/Matam/HW4/Matam_HW4/Players/cmake-build-debug",
		"source" : "/Users/ido/Documents/Matam/HW4/Matam_HW4/Players"
	},
	"version" : 
	{
		"major" : 2,
		"minor" : 7
	}
}
